[1,["3f2l3DfB1Nd7wyYXWutfpM","58bVE24EBIRL2zZ1xfIz6i","beSbhTGSdDQq1BZpVd78d4","48W2QDgllHuoCIHsRZu/d3","905wVHSPpFcIdkF7tCOiwd","dfXy9XeiJKxL+545YYgaY4","5fto1MRm9CtIVtdHDCCYlG","9e5nTG1AJLe7EqRpalPaCb","c1qsE988tMnoSQoqZNUqJ7","caHAczBaJNR433C1DLlg+S","72F/gn+LNO7oOkxV/ugcZl","ea2o8q/hJPqp2KLi8gNJrE","cb0DwHmSVE6KQXqzVPyx55","9et7kh+W5OuYiPCfoAyG/Y","efE1k2q6hG9JUFqz3+rsXk","c7KBo+Y7tGuqxbKDlILqHb","19/egY755LqYVce28s7hNO","283hj1LJFCsoKgF2vFvhhn","fafL0o5w1DvI3IeN5w5T+c","9eO9tkacJPaJWNkSndXTMY"],["value","_textureSetter"],["cc.SpriteFrame",["cc.AnimationClip",["_name","_duration","sample","wrapMode","curveData"],-1,11]],[[1,0,1,2,3,4,5]],[[[[0,"fish24",0.6666666666666666,15,2,[{},"comps",11,[{},"cc.Sprite",11,[{},"spriteFrame",12,[[[{"frame":0},"value",6,0],[{"frame":0.06666666666666667},"value",6,1],[{"frame":0.13333333333333333},"value",6,2],[{"frame":0.2},"value",6,3],[{"frame":0.26666666666666666},"value",6,4],[{"frame":0.3333333333333333},"value",6,5],[{"frame":0.4},"value",6,6],[{"frame":0.4666666666666667},"value",6,7],[{"frame":0.5333333333333333},"value",6,8],[{"frame":0.6},"value",6,9]],11,11,11,11,11,11,11,11,11,11]]]]]],0,0,[0,0,0,0,0,0,0,0,0,0],[0,0,0,0,0,0,0,0,0,0],[0,1,2,3,4,5,6,7,8,9]],[[{"name":"9_00000","rect":[81,8,224,530],"offset":[-8,70.5],"originalSize":[402,687],"capInsets":[0,0,0,0]}],[0],0,[0],[1],[10]],[[{"name":"9_00003","rect":[90,8,223,532],"offset":[0.5,69.5],"originalSize":[402,687],"capInsets":[0,0,0,0]}],[0],0,[0],[1],[11]],[[{"name":"9_00001","rect":[48,8,254,518],"offset":[-26,76.5],"originalSize":[402,687],"capInsets":[0,0,0,0]}],[0],0,[0],[1],[12]],[[{"name":"9_00006","rect":[69,8,264,532],"offset":[0,69.5],"originalSize":[402,687],"capInsets":[0,0,0,0]}],[0],0,[0],[1],[13]],[[{"name":"9_00004","rect":[84,8,237,538],"offset":[1.5,66.5],"originalSize":[402,687],"capInsets":[0,0,0,0]}],[0],0,[0],[1],[14]],[[{"name":"9_00007","rect":[70,8,257,540],"offset":[-2.5,65.5],"originalSize":[402,687],"capInsets":[0,0,0,0]}],[0],0,[0],[1],[15]],[[{"name":"9_00002","rect":[82,8,225,526],"offset":[-6.5,72.5],"originalSize":[402,687],"capInsets":[0,0,0,0]}],[0],0,[0],[1],[16]],[[{"name":"9_00008","rect":[74,8,245,542],"offset":[-4.5,64.5],"originalSize":[402,687],"capInsets":[0,0,0,0]}],[0],0,[0],[1],[17]],[[{"name":"9_00009","rect":[81,8,230,538],"offset":[-5,66.5],"originalSize":[402,687],"capInsets":[0,0,0,0]}],[0],0,[0],[1],[18]],[[{"name":"9_00005","rect":[75,8,253,540],"offset":[0.5,65.5],"originalSize":[402,687],"capInsets":[0,0,0,0]}],[0],0,[0],[1],[19]]]]